linkedlistpy/__init__.py
linkedlistpy/linkedlist.py
linkedlistpy/math.py
linkedlistpy/py.typed
linkedlistpy-0.0.5.dist-info/METADATA
linkedlistpy-0.0.5.dist-info/WHEEL
linkedlistpy-0.0.5.dist-info/top_level.txt
linkedlistpy-0.0.5.dist-info/zip-safe
linkedlistpy-0.0.5.dist-info/RECORD
