Metadata-Version: 2.1
Name: linkedlistpy
Version: 0.0.5
Summary: some useful tools for linked lists
Home-page: UNKNOWN
Author: Packetsss
License: UNKNOWN
Project-URL: Github, https://github.com/packetsss/linkedlistpy
Project-URL: Documentation, https://github.com/packetsss/linkedlistpy/blob/main/README.md
Keywords: python, linked list
Platform: unix
Platform: linux
Platform: osx
Platform: cygwin
Platform: win32
Classifier: Programming Language :: Python :: 3
Classifier: Programming Language :: Python :: 3 :: Only
Classifier: Programming Language :: Python :: 3.8
Requires-Python: >=3.6
Requires-Dist: requests
Provides-Extra: testing
Requires-Dist: pytest (>=6.0) ; extra == 'testing'
Requires-Dist: pytest-cov (>=2.0) ; extra == 'testing'
Requires-Dist: mypy (>=0.910) ; extra == 'testing'
Requires-Dist: flake8 (>=3.9) ; extra == 'testing'
Requires-Dist: tox (>=3.24) ; extra == 'testing'
